amadeusgpt/__init__.py
amadeusgpt/app.py
amadeusgpt/app_utils.py
amadeusgpt/config.py
amadeusgpt/integration_module_hub.py
amadeusgpt/logger.py
amadeusgpt/main.py
amadeusgpt/project.py
amadeusgpt/utils.py
amadeusgpt/version.py
amadeusgpt/analysis_objects/__init__.py
amadeusgpt/analysis_objects/animal.py
amadeusgpt/analysis_objects/base.py
amadeusgpt/analysis_objects/event.py
amadeusgpt/analysis_objects/llm.py
amadeusgpt/analysis_objects/model.py
amadeusgpt/analysis_objects/object.py
amadeusgpt/analysis_objects/relationship.py
amadeusgpt/analysis_objects/visualization.py
amadeusgpt/behavior_analysis/__init__.py
amadeusgpt/behavior_analysis/analysis_factory.py
amadeusgpt/behavior_analysis/animal_behavior_analysis.py
amadeusgpt/behavior_analysis/identifier.py
amadeusgpt/configs/EPM_template.yaml
amadeusgpt/configs/Horse_template.yaml
amadeusgpt/configs/MABe_template.yaml
amadeusgpt/configs/MausHaus_template.yaml
amadeusgpt/integration_modules/__init__.py
amadeusgpt/integration_modules/embedding/__init__.py
amadeusgpt/integration_modules/embedding/cebra.py
amadeusgpt/integration_modules/embedding/transform.py
amadeusgpt/integration_modules/embedding/umap.py
amadeusgpt/integration_modules/kinematics/__init__.py
amadeusgpt/integration_modules/kinematics/gait.py
amadeusgpt/managers/__init__.py
amadeusgpt/managers/animal_manager.py
amadeusgpt/managers/base.py
amadeusgpt/managers/event_manager.py
amadeusgpt/managers/gui_manager.py
amadeusgpt/managers/object_manager.py
amadeusgpt/managers/relationship_manager.py
amadeusgpt/managers/visual_manager.py
amadeusgpt/programs/__init__.py
amadeusgpt/programs/api_registry.py
amadeusgpt/programs/sandbox.py
amadeusgpt/programs/task_program_registry.py
amadeusgpt/static/__init__.py
amadeusgpt/static/customEPMprompt_short.mp4
amadeusgpt/static/images/amadeusgpt_logo.png
amadeusgpt/static/images/cat.png
amadeusgpt/static/images/chatbot.png
amadeusgpt/static/images/supertopview.png
amadeusgpt/static/styles/style.css
amadeusgpt-0.1.3.dist-info/METADATA
amadeusgpt-0.1.3.dist-info/WHEEL
amadeusgpt-0.1.3.dist-info/entry_points.txt
amadeusgpt-0.1.3.dist-info/top_level.txt
amadeusgpt-0.1.3.dist-info/RECORD
