Metadata-Version: 2.1
Name: amadeusgpt
Version: 0.1.3
Summary: AmadeusGPT🎻: We turn natural language descriptions of behaviors into machine-executable code
Home-page: https://github.com/AdaptiveMotorControlLab/AmadeusGPT
Author: Shaokai Ye, Jessy Lauer, Mu Zhou, Alexander Mathis, Mackenzie Mathis
Author-email: mackenzie@post.harvard.edu
License: UNKNOWN
Project-URL: Bug Tracker, https://github.com/AdaptiveMotorControlLab/AmadeusGPT/issues
Platform: UNKNOWN
Classifier: Development Status :: 5 - Production/Stable
Classifier: Environment :: GPU :: NVIDIA CUDA
Classifier: Intended Audience :: Science/Research
Classifier: Operating System :: OS Independent
Classifier: Programming Language :: Python :: 3
Classifier: Topic :: Scientific/Engineering :: Artificial Intelligence
Classifier: License :: OSI Approved :: Apache Software License
Requires-Python: >=3.10
Requires-Dist: openai>=1.0
Requires-Dist: opencv-python-headless
Requires-Dist: cebra>=0.4.0
Requires-Dist: umap-learn
Requires-Dist: cachetools
Requires-Dist: matplotlib<3.9
Requires-Dist: ipympl
Requires-Dist: PyYAML
Requires-Dist: streamlit>=1.26.0
Requires-Dist: streamlit-drawable-canvas==0.9.2
Provides-Extra: dev
Requires-Dist: pylint; extra == "dev"
Requires-Dist: toml; extra == "dev"
Requires-Dist: yapf; extra == "dev"
Requires-Dist: black; extra == "dev"
Requires-Dist: pytest; extra == "dev"
